Code/__init__.py
pysharepi-1.5.dist-info/LICENSE.txt
pysharepi-1.5.dist-info/METADATA
pysharepi-1.5.dist-info/WHEEL
pysharepi-1.5.dist-info/top_level.txt
pysharepi-1.5.dist-info/RECORD
