Metadata-Version: 2.1
Name: pysharepi
Version: 1.5
Summary: Download files from sharepoint site using client id , client secret and tenant id via Azure Active Directory. 
Author: Jeevan V
Author-email: jeevanvsan@gmail.com
Classifier: Programming Language :: Python :: 2
Classifier: License :: OSI Approved :: MIT License
Classifier: Operating System :: OS Independent
License-File: LICENSE.txt
